pocketbase_orm.py
pocketbase_orm-0.16.0.dist-info/licenses/LICENSE
pocketbase_orm-0.16.0.dist-info/WHEEL
pocketbase_orm-0.16.0.dist-info/METADATA
pocketbase_orm-0.16.0.dist-info/RECORD
