Metadata-Version: 2.4
Name: pocketbase-orm
Version: 0.16.0
Summary: Add your description here
Requires-Python: >=3.11
License-File: LICENSE
Requires-Dist: pocketbase>=0.15.0
Requires-Dist: pydantic[email]>=2.10.6
